Metadata-Version: 2.1
Name: tf-cli
Version: 0.0.6
Summary: This contains a CLI for AWS terraform
Home-page: https://github.com/rkline2/tf_cli
Author: Rooklyn Kline
Author-email: 
License: UNKNOWN
Platform: UNKNOWN
Classifier: Programming Language :: Python :: 3
Classifier: License :: OSI Approved :: GNU Affero General Public License v3
Classifier: Operating System :: POSIX :: Linux
Requires-Python: >=3.7
Provides-Extra: dev
